{
  "model_comparison": {
    "gradient_boosting": {
      "mse": 4300226.463450524,
      "rmse": 2073.6987398005826,
      "mae": 312.4649571526038,
      "r2": 0.8562473979492146,
      "mape": 12.274029455502419
    },
    "random_forest": {
      "mse": 6325150.925490716,
      "rmse": 2514.985273414283,
      "mae": 324.1207716311698,
      "r2": 0.788556041959327,
      "mape": 10.996940539057533
    },
    "ridge_regression": {
      "mse": 7848467.89358541,
      "rmse": 2801.5117157680083,
      "mae": 1277.0523966855244,
      "r2": 0.7376329615650878,
      "mape": 229.27172848805748
    }
  },
  "best_model": "gradient_boosting",
  "best_metrics": {
    "mse": 4300226.463450524,
    "rmse": 2073.6987398005826,
    "mae": 312.4649571526038,
    "r2": 0.8562473979492146,
    "mape": 12.274029455502419
  },
  "cross_validation": {
    "folds": 5,
    "r2_scores": [
      0.8562663815060307,
      0.8226140729453979,
      0.9605271638455,
      0.9597192621510958,
      0.9502300368848431
    ],
    "r2_mean": 0.9098713834665734,
    "r2_std": 0.05859517808738112,
    "rmse_mean": 1379.8724233273804,
    "rmse_std": 597.255877576358
  },
  "feature_importance": [
    {
      "feature": "total_revenue",
      "importance": 0.590188169268809
    },
    {
      "feature": "account_age_days",
      "importance": 0.2690183601448618
    },
    {
      "feature": "avg_days_between_orders",
      "importance": 0.09720366767789938
    },
    {
      "feature": "avg_discount_amount",
      "importance": 0.011705819622429985
    },
    {
      "feature": "monetary_avg",
      "importance": 0.007023233847874183
    },
    {
      "feature": "avg_order_value",
      "importance": 0.005860229386850888
    },
    {
      "feature": "max_order_value",
      "importance": 0.0036940972100566656
    },
    {
      "feature": "discount_orders_pct",
      "importance": 0.0032570721336157714
    },
    {
      "feature": "website_visits_30d",
      "importance": 0.0018857204952145083
    },
    {
      "feature": "email_opens_30d",
      "importance": 0.0015964574010435585
    },
    {
      "feature": "first_purchase_value",
      "importance": 0.0015905923746154153
    },
    {
      "feature": "recency_days",
      "importance": 0.001517349008247868
    },
    {
      "feature": "customer_acquisition_cost",
      "importance": 0.0012689496500812387
    },
    {
      "feature": "rfm_score",
      "importance": 0.0009474927124190535
    },
    {
      "feature": "return_rate",
      "importance": 0.0008815713942566275
    }
  ],
  "segment_analysis": [
    {
      "segment": "Low",
      "count": "500",
      "avg_ltv": 264.38234,
      "mae": 35.33324756930173,
      "mape": 15.380308673791749
    },
    {
      "segment": "Medium",
      "count": "500",
      "avg_ltv": 762.54836,
      "mae": 85.99658192762779,
      "mape": 11.310824432372279
    },
    {
      "segment": "High",
      "count": "500",
      "avg_ltv": 1644.6138799999999,
      "mae": 177.09428292914404,
      "mape": 10.82839179379767
    },
    {
      "segment": "Premium",
      "count": "500",
      "avg_ltv": 7088.439380000001,
      "mae": 951.4357161843417,
      "mape": 11.433958114466082
    }
  ],
  "dataset_info": {
    "total_samples": 10000,
    "features": 25,
    "ltv_mean": 2375.316666,
    "ltv_median": 1050.455
  },
  "generated_at": "2026-01-18T17:41:56.272972"
}